[
  {
    "Provider": "TekSavvy",
    "Third Party Internet Provider": "Shaw",
    "Market": "AB / BC",
    "Speed": "60/6",
    "Retail": 59.95,
    "1x Connect. Cost (Trans)": 25.8,
    "1x Connect. Cost (New)": 82.51,
    "Modem Cost": 110,
    "Modem Retail": 143.95,
    "Modem Rental/ Month": "$10",
    "Router Retail": "$59.95",
    "Router Rental": "$10"
  },
  {
    "Provider": "TekSavvy",
    "Third Party Internet Provider": "Shaw",
    "Market": "AB / BC",
    "Speed": "500/100",
    "Retail": "N/A",
    "1x Connect. Cost (Trans)": 25.8,
    "1x Connect. Cost (New)": 82.51,
    "Modem Cost": 110,
    "Modem Retail": 143.95,
    "Modem Rental/ Month": "$10",
    "Router Retail": "$59.95",
    "Router Rental": "$10"
  },
  {
    "Provider": "TekSavvy",
    "Third Party Internet Provider": "Shaw",
    "Market": "AB / BC",
    "Speed": "1G/25",
    "Retail": "N/A",
    "1x Connect. Cost (Trans)": 25.8,
    "1x Connect. Cost (New)": 82.51,
    "Modem Cost": 110,
    "Modem Retail": 143.95,
    "Modem Rental/ Month": "$10",
    "Router Retail": "$59.95",
    "Router Rental": "$10"
  },
  {
    "Provider": "Frontier",
    "Third Party Internet Provider": "Shaw",
    "Market": "AB / BC",
    "Speed": "25/1.5",
    "Retail": 44.95,
    "1x Connect. Cost (Trans)": 20.98,
    "1x Connect. Cost (New)": 79.5,
    "Modem Cost": 110,
    "Modem Retail": 143.95,
    "Modem Rental/ Month": "$10",
    "Router Retail": "$59.95",
    "Router Rental": "$10"
  },
  {
    "Provider": "Frontier",
    "Third Party Internet Provider": "Shaw",
    "Market": "AB / BC",
    "Speed": "30/5",
    "Retail": 49.95,
    "1x Connect. Cost (Trans)": 20.98,
    "1x Connect. Cost (New)": 79.5,
    "Modem Cost": 110,
    "Modem Retail": 143.95,
    "Modem Rental/ Month": "$10",
    "Router Retail": "$59.95",
    "Router Rental": "$10"
  },
  {
    "Provider": "Frontier",
    "Third Party Internet Provider": "Shaw",
    "Market": "AB / BC",
    "Speed": "75/10",
    "Retail": 59.95,
    "1x Connect. Cost (Trans)": 20.98,
    "1x Connect. Cost (New)": 79.5,
    "Modem Cost": 110,
    "Modem Retail": 143.95,
    "Modem Rental/ Month": "$10",
    "Router Retail": "$59.95",
    "Router Rental": "$10"
  },
  {
    "Provider": "Frontier",
    "Third Party Internet Provider": "Shaw",
    "Market": "AB / BC",
    "Speed": "100/10",
    "Retail": 69.95,
    "1x Connect. Cost (Trans)": 20.98,
    "1x Connect. Cost (New)": 79.5,
    "Modem Cost": 110,
    "Modem Retail": 143.95,
    "Modem Rental/ Month": "$10",
    "Router Retail": "$59.95",
    "Router Rental": "$10"
  },
  {
    "Provider": "Frontier",
    "Third Party Internet Provider": "Shaw",
    "Market": "AB / BC",
    "Speed": "150/15",
    "Retail": 84.95,
    "1x Connect. Cost (Trans)": 20.98,
    "1x Connect. Cost (New)": 79.5,
    "Modem Cost": 110,
    "Modem Retail": 143.95,
    "Modem Rental/ Month": "$10",
    "Router Retail": "$59.95",
    "Router Rental": "$10"
  },
  {
    "Provider": "TekSavvy",
    "Third Party Internet Provider": "Eastlink",
    "Market": "NB",
    "Speed": "100/10",
    "Retail": 64.95,
    "1x Connect. Cost (Trans)": 20.98,
    "1x Connect. Cost (New)": 68.32000000000001,
    "Modem Cost": 110,
    "Modem Retail": 143.95,
    "Modem Rental/ Month": "$10",
    "Router Retail": "$59.95",
    "Router Rental": "$10"
  },
  {
    "Provider": "TekSavvy",
    "Third Party Internet Provider": "Eastlink",
    "Market": "NB",
    "Speed": "300/10",
    "Retail": 84.95,
    "1x Connect. Cost (Trans)": 20.98,
    "1x Connect. Cost (New)": 64.94,
    "Modem Cost": 110,
    "Modem Retail": 143.95,
    "Modem Rental/ Month": "$10",
    "Router Retail": "$59.95",
    "Router Rental": "$10"
  },
  {
    "Provider": "TekSavvy",
    "Third Party Internet Provider": "Eastlink",
    "Market": "NB",
    "Speed": "940/15",
    "Retail": 109.95,
    "1x Connect. Cost (Trans)": 20.98,
    "1x Connect. Cost (New)": 68.32000000000001,
    "Modem Cost": 110,
    "Modem Retail": 143.95,
    "Modem Rental/ Month": "$10",
    "Router Retail": "$59.95",
    "Router Rental": "$10"
  },
  {
    "Provider": "TekSavvy",
    "Third Party Internet Provider": "Eastlink",
    "Market": "Newfoundland",
    "Speed": "100/10",
    "Retail": 64.95,
    "1x Connect. Cost (Trans)": 20.98,
    "1x Connect. Cost (New)": 68.32000000000001,
    "Modem Cost": 110,
    "Modem Retail": 143.95,
    "Modem Rental/ Month": "$10",
    "Router Retail": "$59.95",
    "Router Rental": "$10"
  },
  {
    "Provider": "TekSavvy",
    "Third Party Internet Provider": "Eastlink",
    "Market": "Newfoundland",
    "Speed": "300/10",
    "Retail": 84.95,
    "1x Connect. Cost (Trans)": 20.98,
    "1x Connect. Cost (New)": 64.94,
    "Modem Cost": 110,
    "Modem Retail": 143.95,
    "Modem Rental/ Month": "$10",
    "Router Retail": "$59.95",
    "Router Rental": "$10"
  },
  {
    "Provider": "TekSavvy",
    "Third Party Internet Provider": "Eastlink",
    "Market": "Newfoundland",
    "Speed": "940/15",
    "Retail": 109.95,
    "1x Connect. Cost (Trans)": 20.98,
    "1x Connect. Cost (New)": 68.32000000000001,
    "Modem Cost": 110,
    "Modem Retail": 143.95,
    "Modem Rental/ Month": "$10",
    "Router Retail": "$59.95",
    "Router Rental": "$10"
  },
  {
    "Provider": "TekSavvy",
    "Third Party Internet Provider": "Rogers",
    "Market": "Newfoundland",
    "Speed": "30/5",
    "Retail": 59.95,
    "1x Connect. Cost (Trans)": 20.98,
    "1x Connect. Cost (New)": 68.53,
    "Modem Cost": 110,
    "Modem Retail": 143.95,
    "Modem Rental/ Month": "$10",
    "Router Retail": "$59.95",
    "Router Rental": "$10"
  },
  {
    "Provider": "TekSavvy",
    "Third Party Internet Provider": "Rogers",
    "Market": "Newfoundland",
    "Speed": "75/10",
    "Retail": 69.95,
    "1x Connect. Cost (Trans)": 20.98,
    "1x Connect. Cost (New)": 68.53,
    "Modem Cost": 110,
    "Modem Retail": 143.95,
    "Modem Rental/ Month": "$10",
    "Router Retail": "$59.95",
    "Router Rental": "$10"
  },
  {
    "Provider": "Frontier",
    "Third Party Internet Provider": "Eastlink",
    "Market": "Nova Scotia",
    "Speed": "100/10",
    "Retail": 64.95,
    "1x Connect. Cost (Trans)": 20.98,
    "1x Connect. Cost (New)": 64.94,
    "Modem Cost": 110,
    "Modem Retail": 143.95,
    "Modem Rental/ Month": "$10",
    "Router Retail": "$59.95",
    "Router Rental": "$10"
  },
  {
    "Provider": "Frontier",
    "Third Party Internet Provider": "Eastlink",
    "Market": "Nova Scotia",
    "Speed": "150/10",
    "Retail": 74.95,
    "1x Connect. Cost (Trans)": 20.98,
    "1x Connect. Cost (New)": 64.94,
    "Modem Cost": 110,
    "Modem Retail": 143.95,
    "Modem Rental/ Month": "$10",
    "Router Retail": "$59.95",
    "Router Rental": "$10"
  },
  {
    "Provider": "Frontier",
    "Third Party Internet Provider": "Eastlink",
    "Market": "Nova Scotia",
    "Speed": "300/10",
    "Retail": 79.95,
    "1x Connect. Cost (Trans)": 20.98,
    "1x Connect. Cost (New)": 64.94,
    "Modem Cost": 110,
    "Modem Retail": 143.95,
    "Modem Rental/ Month": "$10",
    "Router Retail": "$59.95",
    "Router Rental": "$10"
  },
  {
    "Provider": "TekSavvy",
    "Third Party Internet Provider": "Eastlink",
    "Market": "Nova Scotia",
    "Speed": "940/15",
    "Retail": 109.95,
    "1x Connect. Cost (Trans)": 20.98,
    "1x Connect. Cost (New)": 68.32000000000001,
    "Modem Cost": 110,
    "Modem Retail": 143.95,
    "Modem Rental/ Month": "$10",
    "Router Retail": "$59.95",
    "Router Rental": "$10"
  },
  {
    "Provider": "TekSavvy",
    "Third Party Internet Provider": "Eastlink",
    "Market": "Ontario",
    "Speed": "940/15",
    "Retail": 109.95,
    "1x Connect. Cost (Trans)": 20.98,
    "1x Connect. Cost (New)": 68.32000000000001,
    "Modem Cost": 110,
    "Modem Retail": 143.95,
    "Modem Rental/ Month": "$10",
    "Router Retail": "$59.95",
    "Router Rental": "$10"
  },
  {
    "Provider": "TekSavvy",
    "Third Party Internet Provider": "Cogeco",
    "Market": "Ontario",
    "Speed": "40/10",
    "Retail": 44.95,
    "1x Connect. Cost (Trans)": 22.720000000000002,
    "1x Connect. Cost (New)": 68.32000000000001,
    "Modem Cost": 41,
    "Modem Retail": 79.95,
    "Modem Rental/ Month": "$10",
    "Router Retail": "$59.95",
    "Router Rental": "$10"
  },
  {
    "Provider": "TekSavvy",
    "Third Party Internet Provider": "Cogeco",
    "Market": "Ontario",
    "Speed": "60/10",
    "Retail": 59.95,
    "1x Connect. Cost (Trans)": 22.720000000000002,
    "1x Connect. Cost (New)": 68.32000000000001,
    "Modem Cost": 41,
    "Modem Retail": 79.95,
    "Modem Rental/ Month": "$10",
    "Router Retail": "$59.95",
    "Router Rental": "$10"
  },
  {
    "Provider": "TekSavvy",
    "Third Party Internet Provider": "Cogeco",
    "Market": "Ontario",
    "Speed": "120/10",
    "Retail": 79.95,
    "1x Connect. Cost (Trans)": 22.720000000000002,
    "1x Connect. Cost (New)": 68.32000000000001,
    "Modem Cost": 110,
    "Modem Retail": 143.95,
    "Modem Rental/ Month": "$10",
    "Router Retail": "$59.95",
    "Router Rental": "$10"
  },
  {
    "Provider": "TekSavvy",
    "Third Party Internet Provider": "Cogeco",
    "Market": "Ontario",
    "Speed": "360/30",
    "Retail": 89.5,
    "1x Connect. Cost (Trans)": 22.720000000000002,
    "1x Connect. Cost (New)": 68.32000000000001,
    "Modem Cost": 110,
    "Modem Retail": 143.95,
    "Modem Rental/ Month": "$10",
    "Router Retail": "$59.95",
    "Router Rental": "$10"
  },
  {
    "Provider": "TekSavvy",
    "Third Party Internet Provider": "Cogeco",
    "Market": "Ontario",
    "Speed": "1G/30",
    "Retail": 94.95,
    "1x Connect. Cost (Trans)": 22.720000000000002,
    "1x Connect. Cost (New)": 68.32000000000001,
    "Modem Cost": 110,
    "Modem Retail": 143.95,
    "Modem Rental/ Month": "$10",
    "Router Retail": "$59.95",
    "Router Rental": "$10"
  },
  {
    "Provider": "TekSavvy",
    "Third Party Internet Provider": "Rogers",
    "Market": "Ontario",
    "Speed": "30/10",
    "Retail": 49.95,
    "1x Connect. Cost (Trans)": 20.98,
    "1x Connect. Cost (New)": 68.53,
    "Modem Cost": 110,
    "Modem Retail": 143.95,
    "Modem Rental/ Month": "$10",
    "Router Retail": "$59.95",
    "Router Rental": "$10"
  },
  {
    "Provider": "TekSavvy",
    "Third Party Internet Provider": "Rogers",
    "Market": "Ontario",
    "Speed": "75/30",
    "Retail": 64.95,
    "1x Connect. Cost (Trans)": 20.98,
    "1x Connect. Cost (New)": 68.53,
    "Modem Cost": 110,
    "Modem Retail": 143.95,
    "Modem Rental/ Month": "$10",
    "Router Retail": "$59.95",
    "Router Rental": "$10"
  },
  {
    "Provider": "TekSavvy",
    "Third Party Internet Provider": "Rogers",
    "Market": "Ontario",
    "Speed": "300/30",
    "Retail": 95.95,
    "1x Connect. Cost (Trans)": 20.98,
    "1x Connect. Cost (New)": 68.53,
    "Modem Cost": 110,
    "Modem Retail": 143.95,
    "Modem Rental/ Month": "$10",
    "Router Retail": "$59.95",
    "Router Rental": "$10"
  },
  {
    "Provider": "TekSavvy",
    "Third Party Internet Provider": "Rogers",
    "Market": "Ontario",
    "Speed": "500/30",
    "Retail": 114.95,
    "1x Connect. Cost (Trans)": 20.98,
    "1x Connect. Cost (New)": 68.53,
    "Modem Cost": 110,
    "Modem Retail": 143.95,
    "Modem Rental/ Month": "$10",
    "Router Retail": "$59.95",
    "Router Rental": "$10"
  },
  {
    "Provider": "Frontier",
    "Third Party Internet Provider": "Cogeco",
    "Market": "Ontario",
    "Speed": "6/1",
    "Retail": 34.95,
    "1x Connect. Cost (Trans)": 20,
    "1x Connect. Cost (New)": 65.16,
    "Modem Cost": 110,
    "Modem Retail": 143.95,
    "Modem Rental/ Month": "$10",
    "Router Retail": "$59.95",
    "Router Rental": "$10"
  },
  {
    "Provider": "Frontier",
    "Third Party Internet Provider": "Cogeco",
    "Market": "Ontario",
    "Speed": "15/1",
    "Retail": 39.95,
    "1x Connect. Cost (Trans)": 20,
    "1x Connect. Cost (New)": 65.16,
    "Modem Cost": 110,
    "Modem Retail": 143.95,
    "Modem Rental/ Month": "$10",
    "Router Retail": "$59.95",
    "Router Rental": "$10"
  },
  {
    "Provider": "Frontier",
    "Third Party Internet Provider": "Cogeco",
    "Market": "Ontario",
    "Speed": "40/10",
    "Retail": 44.95,
    "1x Connect. Cost (Trans)": 20,
    "1x Connect. Cost (New)": 65.16,
    "Modem Cost": 110,
    "Modem Retail": 143.95,
    "Modem Rental/ Month": "$10",
    "Router Retail": "$59.95",
    "Router Rental": "$10"
  },
  {
    "Provider": "Frontier",
    "Third Party Internet Provider": "Cogeco",
    "Market": "Ontario",
    "Speed": "60/10",
    "Retail": 59.95,
    "1x Connect. Cost (Trans)": 10,
    "1x Connect. Cost (New)": 65.16,
    "Modem Cost": 110,
    "Modem Retail": 143.95,
    "Modem Rental/ Month": "$10",
    "Router Retail": "$59.95",
    "Router Rental": "$10"
  },
  {
    "Provider": "Frontier",
    "Third Party Internet Provider": "Cogeco",
    "Market": "Ontario",
    "Speed": "120/10",
    "Retail": 79.95,
    "1x Connect. Cost (Trans)": 20,
    "1x Connect. Cost (New)": 65.16,
    "Modem Cost": 110,
    "Modem Retail": 143.95,
    "Modem Rental/ Month": "$10",
    "Router Retail": "$59.95",
    "Router Rental": "$10"
  },
  {
    "Provider": "Frontier",
    "Third Party Internet Provider": "Cogeco",
    "Market": "Ontario",
    "Speed": "180/10",
    "Retail": 94.95,
    "1x Connect. Cost (Trans)": 20,
    "1x Connect. Cost (New)": 65.16,
    "Modem Cost": 110,
    "Modem Retail": 143.95,
    "Modem Rental/ Month": "$10",
    "Router Retail": "$59.95",
    "Router Rental": "$10"
  },
  {
    "Provider": "Frontier",
    "Third Party Internet Provider": "Cogeco",
    "Market": "Ontario",
    "Speed": "250/20",
    "Retail": 94.95,
    "1x Connect. Cost (Trans)": 20,
    "1x Connect. Cost (New)": 65.16,
    "Modem Cost": 110,
    "Modem Retail": 143.95,
    "Modem Rental/ Month": "$10",
    "Router Retail": "$59.95",
    "Router Rental": "$10"
  },
  {
    "Provider": "Frontier",
    "Third Party Internet Provider": "Cogeco",
    "Market": "Ontario",
    "Speed": "360/30",
    "Retail": 94.95,
    "1x Connect. Cost (Trans)": 20,
    "1x Connect. Cost (New)": 65.16,
    "Modem Cost": 110,
    "Modem Retail": 143.95,
    "Modem Rental/ Month": "$10",
    "Router Retail": "$59.95",
    "Router Rental": "$10"
  },
  {
    "Provider": "Frontier",
    "Third Party Internet Provider": "Cogeco",
    "Market": "Ontario",
    "Speed": "1G/30",
    "Retail": 99.95,
    "1x Connect. Cost (Trans)": 20,
    "1x Connect. Cost (New)": 65.16,
    "Modem Cost": 110,
    "Modem Retail": 143.95,
    "Modem Rental/ Month": "$10",
    "Router Retail": "$59.95",
    "Router Rental": "$10"
  },
  {
    "Provider": "Frontier",
    "Third Party Internet Provider": "Eastlink",
    "Market": "Simcoe Ontario",
    "Speed": "100/10",
    "Retail": 59.95,
    "1x Connect. Cost (Trans)": 20.98,
    "1x Connect. Cost (New)": 64.94,
    "Modem Cost": 110,
    "Modem Retail": 143.95,
    "Modem Rental/ Month": "$10",
    "Router Retail": "$59.95",
    "Router Rental": "$10"
  },
  {
    "Provider": "Frontier",
    "Third Party Internet Provider": "Eastlink",
    "Market": "Simcoe Ontario",
    "Speed": "150/10",
    "Retail": 69.95,
    "1x Connect. Cost (Trans)": 20.98,
    "1x Connect. Cost (New)": 64.94,
    "Modem Cost": 110,
    "Modem Retail": 143.95,
    "Modem Rental/ Month": "$10",
    "Router Retail": "$59.95",
    "Router Rental": "$10"
  },
  {
    "Provider": "Frontier",
    "Third Party Internet Provider": "Eastlink",
    "Market": "Simcoe Ontario",
    "Speed": "300/10",
    "Retail": 69.95,
    "1x Connect. Cost (Trans)": 20.98,
    "1x Connect. Cost (New)": 64.94,
    "Modem Cost": 110,
    "Modem Retail": 143.95,
    "Modem Rental/ Month": "$10",
    "Router Retail": "$59.95",
    "Router Rental": "$10"
  },
  {
    "Provider": "Frontier",
    "Third Party Internet Provider": "Rogers",
    "Market": "Ontario",
    "Speed": "30/5",
    "Retail": 59.95,
    "1x Connect. Cost (Trans)": 20.98,
    "1x Connect. Cost (New)": 65.16,
    "Modem Cost": 110,
    "Modem Retail": 143.95,
    "Modem Rental/ Month": "$10",
    "Router Retail": "$59.95",
    "Router Rental": "$10"
  },
  {
    "Provider": "Frontier",
    "Third Party Internet Provider": "Rogers",
    "Market": "Ontario",
    "Speed": "75/10",
    "Retail": 64.95,
    "1x Connect. Cost (Trans)": 20.98,
    "1x Connect. Cost (New)": 65.16,
    "Modem Cost": 110,
    "Modem Retail": 143.95,
    "Modem Rental/ Month": "$10",
    "Router Retail": "$59.95",
    "Router Rental": "$10"
  },
  {
    "Provider": "Frontier",
    "Third Party Internet Provider": "Rogers",
    "Market": "Ontario",
    "Speed": "300/20",
    "Retail": 95.95,
    "1x Connect. Cost (Trans)": 20.98,
    "1x Connect. Cost (New)": 65.16,
    "Modem Cost": 110,
    "Modem Retail": 143.95,
    "Modem Rental/ Month": "$10",
    "Router Retail": "$59.95",
    "Router Rental": "$10"
  },
  {
    "Provider": "Frontier",
    "Third Party Internet Provider": "Rogers",
    "Market": "Ontario",
    "Speed": "500/20",
    "Retail": 104.95,
    "1x Connect. Cost (Trans)": 20.98,
    "1x Connect. Cost (New)": 65.16,
    "Modem Cost": 110,
    "Modem Retail": 143.95,
    "Modem Rental/ Month": "$10",
    "Router Retail": "$59.95",
    "Router Rental": "$10"
  },
  {
    "Provider": "Frontier",
    "Third Party Internet Provider": "Rogers",
    "Market": "Ontario",
    "Speed": "1G/20",
    "Retail": 114.95,
    "1x Connect. Cost (Trans)": 20.98,
    "1x Connect. Cost (New)": 65.16,
    "Modem Cost": 110,
    "Modem Retail": 143.95,
    "Modem Rental/ Month": "$10",
    "Router Retail": "$59.95",
    "Router Rental": "$10"
  },
  {
    "Provider": "TekSavvy",
    "Third Party Internet Provider": "Eastlink",
    "Market": "PEI",
    "Speed": "100/10",
    "Retail": 64.95,
    "1x Connect. Cost (Trans)": 20.98,
    "1x Connect. Cost (New)": 68.32000000000001,
    "Modem Cost": 110,
    "Modem Retail": 143.95,
    "Modem Rental/ Month": "$10",
    "Router Retail": "$59.95",
    "Router Rental": "$10"
  },
  {
    "Provider": "TekSavvy",
    "Third Party Internet Provider": "Eastlink",
    "Market": "PEI",
    "Speed": "300/10",
    "Retail": 84.95,
    "1x Connect. Cost (Trans)": 20.98,
    "1x Connect. Cost (New)": 64.94,
    "Modem Cost": 110,
    "Modem Retail": 143.95,
    "Modem Rental/ Month": "$10",
    "Router Retail": "$59.95",
    "Router Rental": "$10"
  },
  {
    "Provider": "TekSavvy",
    "Third Party Internet Provider": "Eastlink",
    "Market": "PEI",
    "Speed": "940/15",
    "Retail": 109.95,
    "1x Connect. Cost (Trans)": 20.98,
    "1x Connect. Cost (New)": 68.32000000000001,
    "Modem Cost": 110,
    "Modem Retail": 143.95,
    "Modem Rental/ Month": "$10",
    "Router Retail": "$59.95",
    "Router Rental": "$10"
  },
  {
    "Provider": "TekSavvy",
    "Third Party Internet Provider": "Videotron",
    "Market": "Quebec",
    "Speed": "30/10",
    "Retail": 49.95,
    "1x Connect. Cost (Trans)": 27.1,
    "1x Connect. Cost (New)": 87.93,
    "Modem Cost": 84.95,
    "Modem Retail": 89.95,
    "Modem Rental/ Month": "$10",
    "Router Retail": "$59.95",
    "Router Rental": "$10"
  },
  {
    "Provider": "TekSavvy",
    "Third Party Internet Provider": "Videotron",
    "Market": "Quebec",
    "Speed": "60/10",
    "Retail": 54.95,
    "1x Connect. Cost (Trans)": 27.1,
    "1x Connect. Cost (New)": 87.93,
    "Modem Cost": 84.95,
    "Modem Retail": 89.95,
    "Modem Rental/ Month": "$10",
    "Router Retail": "$59.95",
    "Router Rental": "$10"
  },
  {
    "Provider": "TekSavvy",
    "Third Party Internet Provider": "Videotron",
    "Market": "Quebec",
    "Speed": "120/10",
    "Retail": 64.95,
    "1x Connect. Cost (Trans)": 27.1,
    "1x Connect. Cost (New)": 87.93,
    "Modem Cost": 84.95,
    "Modem Retail": 89.95,
    "Modem Rental/ Month": "$10",
    "Router Retail": "$59.95",
    "Router Rental": "$10"
  },
  {
    "Provider": "TekSavvy",
    "Third Party Internet Provider": "Videotron",
    "Market": "Quebec",
    "Speed": "200/30",
    "Retail": "N/A",
    "1x Connect. Cost (Trans)": 27.1,
    "1x Connect. Cost (New)": 87.93,
    "Modem Cost": 84.95,
    "Modem Retail": 89.95,
    "Modem Rental/ Month": "$10",
    "Router Retail": "$59.95",
    "Router Rental": "$10"
  },
  {
    "Provider": "TekSavvy",
    "Third Party Internet Provider": "Videotron",
    "Market": "Quebec",
    "Speed": "400/50",
    "Retail": "N/A",
    "1x Connect. Cost (Trans)": 27.1,
    "1x Connect. Cost (New)": 87.93,
    "Modem Cost": 84.95,
    "Modem Retail": 89.95,
    "Modem Rental/ Month": "$10",
    "Router Retail": "$59.95",
    "Router Rental": "$10"
  },
  {
    "Provider": "TekSavvy",
    "Third Party Internet Provider": "Shaw",
    "Market": "West ON, MB",
    "Speed": "30/5",
    "Retail": 49.95,
    "1x Connect. Cost (Trans)": 20.98,
    "1x Connect. Cost (New)": 82.51,
    "Modem Cost": 110,
    "Modem Retail": 143.95,
    "Modem Rental/ Month": "$10",
    "Router Retail": "$59.95",
    "Router Rental": "$10"
  },
  {
    "Provider": "TekSavvy",
    "Third Party Internet Provider": "Shaw",
    "Market": "West ON, MB",
    "Speed": "60/6",
    "Retail": 59.95,
    "1x Connect. Cost (Trans)": 25.8,
    "1x Connect. Cost (New)": 82.51,
    "Modem Cost": 110,
    "Modem Retail": 143.95,
    "Modem Rental/ Month": "$10",
    "Router Retail": "$59.95",
    "Router Rental": "$10"
  },
  {
    "Provider": "TekSavvy",
    "Third Party Internet Provider": "Shaw",
    "Market": "West ON, MB",
    "Speed": "100/10",
    "Retail": 74.95,
    "1x Connect. Cost (Trans)": 25.8,
    "1x Connect. Cost (New)": 82.51,
    "Modem Cost": 110,
    "Modem Retail": 143.95,
    "Modem Rental/ Month": "$10",
    "Router Retail": "$59.95",
    "Router Rental": "$10"
  },
  {
    "Provider": "TekSavvy",
    "Third Party Internet Provider": "Shaw",
    "Market": "West ON, MB",
    "Speed": "500/100",
    "Retail": "N/A",
    "1x Connect. Cost (Trans)": 25.8,
    "1x Connect. Cost (New)": 82.51,
    "Modem Cost": 110,
    "Modem Retail": 143.95,
    "Modem Rental/ Month": "$10",
    "Router Retail": "$59.95",
    "Router Rental": "$10"
  },
  {
    "Provider": "TekSavvy",
    "Third Party Internet Provider": "Shaw",
    "Market": "West ON, MB",
    "Speed": "1G/25",
    "Retail": "N/A",
    "1x Connect. Cost (Trans)": 25.8,
    "1x Connect. Cost (New)": 82.51,
    "Modem Cost": 110,
    "Modem Retail": 143.95,
    "Modem Rental/ Month": "$10",
    "Router Retail": "$59.95",
    "Router Rental": "$10"
  }
]